KingdomsAndWarfare/Kingdoms/Kingdom.py
KingdomsAndWarfare/Kingdoms/__init__.py
KingdomsAndWarfare/Traits/Trait.py
KingdomsAndWarfare/Traits/__init__.py
KingdomsAndWarfare/Units/Aerial.py
KingdomsAndWarfare/Units/Artillery.py
KingdomsAndWarfare/Units/Cavalry.py
KingdomsAndWarfare/Units/Infantry.py
KingdomsAndWarfare/Units/Unit.py
KingdomsAndWarfare/Units/UnitFactory.py
KingdomsAndWarfare/Units/__init__.py
KingdomsAndWarfare-0.2.4.dist-info/METADATA
KingdomsAndWarfare-0.2.4.dist-info/WHEEL
KingdomsAndWarfare-0.2.4.dist-info/top_level.txt
KingdomsAndWarfare-0.2.4.dist-info/RECORD
